{ 
   "type":"cosmos-sdk/StdTx",
   "value":{ 
      "msg":[ 
         { 
            "type":"cosmos-sdk/MsgCreateValidator",
            "value":{ 
               "description":{ 
                  "moniker":"witval",
                  "identity":"",
                  "website":"",
                  "security_contact":"",
                  "details":""
               },
               "commission":{ 
                  "rate":"0.100000000000000000",
                  "max_rate":"0.200000000000000000",
                  "max_change_rate":"0.010000000000000000"
               },
               "min_self_delegation":"1",
               "delegator_address":"kava1gncnmsxq8gf3yh9r0nvr7qmwfu5ahs58068kd8",
               "validator_address":"kavavaloper1gncnmsxq8gf3yh9r0nvr7qmwfu5ahs58zva74s",
               "pubkey":"kavavalconspub1zcjduepqypyhf7fdpclwdmhk89e982fl0xhyl40f6ecxj5c5s3rx9sl96rlsqzanmy",
               "value":{ 
                  "denom":"ukava",
                  "amount":"1000000000000"
               }
            }
         }
      ],
      "fee":{ 
         "amount":[ 

         ],
         "gas":"200000"
      },
      "signatures":[ 
         { 
            "pub_key":{ 
               "type":"tendermint/PubKeySecp256k1",
               "value":"AuznmUF230Pnmk2EcljaiZRJns+ZN4usKK1iKA7YhnMD"
            },
            "signature":"FEGy772rg+IOSGKJH8bY8rLZnKCW+94+IpVtrad7j0AFo8S70LeXDnMGiPbn2te1PTBEwuFMZeV1MRTYLeeYwg=="
         }
      ],
      "memo":"ccfe9885b3919cb6772dbb9d703c8bae9cb86b9e@45.79.34.146:26656"
   }
}
